{
  "config": {
    "stylesheet": "/georchestra.css",
    "logoUrl": "/jDev.logo_globe.white.png",
    "hideLogin": false,
    "iconsUrl": "/",
    "lang": "fr"
  },
  "menu": [
    {
      "label": "Catalogue",
      "i18n": "catalogue",
      "url": "/geoserver/datahub",
      "activeAppUrl": "/datahub"
    },
    {
      "label": "Visualiseur",
      "i18n": "viewer",
      "url": "/geoserver/web",
      "activeAppUrl": "/web"
    },
    {
      "label": "Cartes",
      "i18n": "map",
      "url": "https://google.com",
      "activeAppUrl": "/map"
    },
    {
      "label": "Applications",
      "i18n": "apps",
      "url": "/geoserver/app",
      "activeAppUrl": "/app"
    },
    {
      "label": "Services",
      "i18n": "services",
      "url": "/geoserver/service",
      "activeAppUrl": "/service"
    },
    {
      "type": "separator",
      "hasRole": "ROLE_GN_EDITOR",
      "blockedRole": "ROLE_SUPERUSER, ROLE_GN_REVIEWER, ROLE_GN_ADMIN"
    },
    {
      "type": "dropdown",
      "label": "Outils d'administration",
      "hasRole": "ROLE_GN_EDITOR",
      "blockedRole": "ROLE_SUPERUSER, ROLE_GN_REVIEWER, ROLE_GN_ADMIN",
      "items": [
        {
          "label": "Catalogue",
          "i18n": "catalogue",
          "url": "/console/manager/home",
          "activeAppUrl": "/link1",
          "icon": "folder-open-regular.svg"
        },
        {
          "label": "Visualiseur",
          "i18n": "visualiseur",
          "url": "",
          "activeAppUrl": "/link2",
          "icon": "eye-solid.svg"
        },
        {
          "label": "Analytics",
          "i18n": "analytics",
          "url": "",
          "activeAppUrl": "/link3",
          "icon": "chart-line-solid.svg"
        },
        {
          "label": "Utilisateurs",
          "i18n": "users",
          "url": "",
          "activeAppUrl": "/link4",
          "icon": "users-solid.svg"
        }
      ]
    }
  ]
}
